spark_submit_app_id_wrapper-0.1.0.dist-info/DESCRIPTION.rst
spark_submit_app_id_wrapper-0.1.0.dist-info/METADATA
spark_submit_app_id_wrapper-0.1.0.dist-info/RECORD
spark_submit_app_id_wrapper-0.1.0.dist-info/WHEEL
spark_submit_app_id_wrapper-0.1.0.dist-info/entry_points.txt
spark_submit_app_id_wrapper-0.1.0.dist-info/metadata.json
spark_submit_app_id_wrapper-0.1.0.dist-info/top_level.txt
ssaiw/__init__.py
