Metadata-Version: 2.0
Name: spark-submit-app-id-wrapper
Version: 0.1.0
Summary: 
